bindep/__init__.py
bindep/__main__.py
bindep/depends.py
bindep/tests/__init__.py
bindep/tests/bindep.txt
bindep/tests/test_depends.py
bindep/tests/test_main.py
bindep/tests/fixtures/almalinux/etc/os-release
bindep/tests/fixtures/alpine/etc/os-release
bindep/tests/fixtures/amazonami/etc/os-release
bindep/tests/fixtures/arch/etc/os-release
bindep/tests/fixtures/centos/etc/os-release
bindep/tests/fixtures/debiansid/etc/os-release
bindep/tests/fixtures/fedora23/etc/os-release
bindep/tests/fixtures/manjaro/etc/os-release
bindep/tests/fixtures/opensuseleap/etc/os-release
bindep/tests/fixtures/opensuseleap15/etc/os-release
bindep/tests/fixtures/oraclelinux/etc/os-release
bindep/tests/fixtures/rhel8/etc/os-release
bindep/tests/fixtures/rhelserver7/etc/os-release
bindep/tests/fixtures/rhelworkstation7/etc/os-release
bindep/tests/fixtures/rocky/etc/os-release
bindep/tests/fixtures/sles/etc/os-release
bindep/tests/fixtures/ubuntu/etc/os-release
bindep/tests/fixtures/unknown/etc/os-release
bindep-2.13.0.dist-info/licenses/AUTHORS
bindep-2.13.0.dist-info/licenses/LICENSE
bindep-2.13.0.dist-info/METADATA
bindep-2.13.0.dist-info/WHEEL
bindep-2.13.0.dist-info/entry_points.txt
bindep-2.13.0.dist-info/pbr.json
bindep-2.13.0.dist-info/top_level.txt
bindep-2.13.0.dist-info/RECORD
