Metadata-Version: 2.4
Name: bindep
Version: 2.13.0
Summary: Binary dependency utility
Author: OpenDev Contributors
Author-email: service-discuss@lists.opendev.org
Maintainer: OpenDev Contributors
Maintainer-email: service-discuss@lists.opendev.org
Project-URL: Browse Source, https://opendev.org/opendev/bindep
Project-URL: Bug Reporting, https://storyboard.openstack.org/#!/project/opendev/bindep
Project-URL: Documentation, https://docs.opendev.org/opendev/bindep
Project-URL: Git Clone URL, https://opendev.org/opendev/bindep
Project-URL: License Texts, https://opendev.org/opendev/bindep/src/branch/master/LICENSE
Project-URL: Release Notes, https://docs.opendev.org/opendev/bindep/latest/releasenotes.html
Keywords: binary,commandline,dependency,distribution,distro,package
Classifier: Development Status :: 5 - Production/Stable
Classifier: Environment :: Console
Classifier: Intended Audience :: Developers
Classifier: Intended Audience :: Information Technology
Classifier: License :: OSI Approved :: Apache Software License
Classifier: Operating System :: MacOS :: MacOS X
Classifier: Operating System :: POSIX :: Linux
Classifier: Programming Language :: Python :: 3
Classifier: Programming Language :: Python :: 3.7
Classifier: Programming Language :: Python :: 3.8
Classifier: Programming Language :: Python :: 3.9
Classifier: Programming Language :: Python :: 3.10
Classifier: Programming Language :: Python :: 3.11
Classifier: Programming Language :: Python :: 3.12
Classifier: Programming Language :: Python :: 3.13
Classifier: Programming Language :: Python :: Implementation :: CPython
Classifier: Topic :: Software Development :: Quality Assurance
Classifier: Topic :: Software Development :: Testing
Classifier: Topic :: System :: Archiving :: Packaging
Classifier: Topic :: Utilities
Requires-Python: >=3.7
License-File: LICENSE
Requires-Dist: distro>=1.7
Requires-Dist: packaging
Requires-Dist: Parsley
Requires-Dist: pbr>=2
Provides-Extra: build-docs
Requires-Dist: fixtures>=0.3.12; extra == "build-docs"
Requires-Dist: reno>=2.8.0; extra == "build-docs"
Requires-Dist: sphinx!=1.6.6,!=1.6.7,!=2.1.0; extra == "build-docs"
Requires-Dist: sphinxcontrib-programoutput; extra == "build-docs"
Provides-Extra: test-cover
Requires-Dist: bindep[test-unit]; extra == "test-cover"
Requires-Dist: coverage>=3.6; extra == "test-cover"
Provides-Extra: test-linters
Requires-Dist: hacking<8,>=7; extra == "test-linters"
Provides-Extra: test-unit
Requires-Dist: fixtures>=0.3.12; extra == "test-unit"
Requires-Dist: python-subunit; extra == "test-unit"
Requires-Dist: stestr>=1; extra == "test-unit"
Requires-Dist: testtools>=0.9.27; extra == "test-unit"
Dynamic: license-file
